chunk_embed/__init__.py
chunk_embed/__main__.py
chunk_embed/server.py
chunk_embed-0.1.0.dist-info/METADATA
chunk_embed-0.1.0.dist-info/WHEEL
chunk_embed-0.1.0.dist-info/entry_points.txt
chunk_embed-0.1.0.dist-info/top_level.txt
chunk_embed-0.1.0.dist-info/RECORD
