Metadata-Version: 2.4
Name: chunk-embed
Version: 0.1.0
Summary: Chunk Embed Store - Chunk & Embed Knowledge Base
Author-email: Aditya Mishra <adi.mishra989@gmail.com>
License-Expression: MIT
Classifier: Development Status :: 3 - Alpha
Classifier: Intended Audience :: Developers
Classifier: Programming Language :: Python :: 3
Classifier: Programming Language :: Python :: 3.8
Classifier: Programming Language :: Python :: 3.9
Classifier: Programming Language :: Python :: 3.10
Classifier: Programming Language :: Python :: 3.11
Requires-Python: >=3.10
Requires-Dist: sentence-transformers==3.3.1
Requires-Dist: chromadb==0.6.3
Requires-Dist: psutil==6.1.1
Requires-Dist: tqdm==4.67.1
